boto3helper/__init__.py
boto3helper/cloudwatchlogs_helper.py
boto3helper/ec2_helper.py
boto3helper/emr_helper.py
boto3helper-0.1.4.dist-info/DESCRIPTION.rst
boto3helper-0.1.4.dist-info/METADATA
boto3helper-0.1.4.dist-info/RECORD
boto3helper-0.1.4.dist-info/WHEEL
boto3helper-0.1.4.dist-info/metadata.json
boto3helper-0.1.4.dist-info/top_level.txt
