Metadata-Version: 2.0
Name: boto3helper
Version: 0.1.4
Summary: boto3 helper classes
Home-page: https://github.com/Hiroyama-Yutaka/boto3helper.git
Author: Yutaka Hiroyama
Author-email: hiroyama@mbk.nifty.com
License: MIT
Keywords: AWS
Platform: UNKNOWN
Classifier: Development Status :: 4 - Beta
Classifier: Intended Audience :: Developers
Classifier: Topic :: Software Development :: Build Tools
Classifier: License :: OSI Approved :: MIT License
Classifier: Programming Language :: Python
Requires-Dist: boto3
Requires-Dist: botocore
